Workbook

Sheet Instructions
B1: Scarborough Glen Condo Association IV
B2: Capital Reserve Funding Plan
B4: How to read this workbook
B5: START on the 'Fund Summary' tab — it shows the three funds, their targets/floors, the
B6: per-unit monthly funding, and the 'Reserve Funding Status' all on one page.
B7: The three fund tabs — Emergency Reserve, Long-Term Maintenance, Operating Reserve — each
B8: show that fund's year-by-year balance from 2027 to 2050.
B9: 'Components' lists every capital item and its cost; 'Expenditure Chart' plots spending by year.
B10: Yellow cells are inputs you can edit; every other cell is calculated automatically.
B12: Data Sources:
B13: Based on Becht Engineering Capital Reserve Study (Project 25-1140, February 2026)
B14: Entity allocations derived from Falcon Group Report (2022) per-entity quantity ratios
... B58: See the 'Components' sheet for full detail. Summary:
B60: Component | C60: Allocated Cost | D60: Replacement Year
B61: Siding, Vinyl (Condo IV share) | C61: 1651860 | D61: 2049
B62: Roof, Shingles - Townhouses (Condo IV share) | C62: 880045 | D62: 2050
B63: Deck Framing & Footings, Wood (Condo IV share) | C63: 149760 | D63: 2033
B64: Deck Boards (surface), Wood (Condo IV share) | C64: 131040 | D64: 2033
B65: Deck Railings & Balusters, Wood (Condo IV share) (safety) | C65: 93600 | D65: 2033
B66: Deck Railings — 2027 remaining replacements (5 rails) | C66: 22500 | D66: 2027
B67: Deck Replacement, Composite (Condo IV share) | C67: 132444 | D67: 2053
B68: Chimney Chase Covers (Condo IV share) | C68: 125160 | D68: 2031
B69: Entry Stoops — Concrete Replacement | C69: 196000 | D69: 2032
B70: Entry Stoops — Leveling & Stair Nosing (safety) | C70: 29400 | D70: 2028
B71: Exterior Caulk/Sealant & Trim Maintenance | C71: 15000 | D71: 2027
B72: Window Wells — rebuild program, 2027 (6 wells) | C72: 48000 | D72: 2027
B73: Window Wells — rebuild program, 2028 (15 wells) | C73: 120000 | D73: 2028
B75: Items NOT Included (Budget Separately)
B76: The following items from the Falcon 2022 report are NOT in the Becht 2026 study and are therefore NOT included in this funding schedule. Consider budgeting for these items separately.
B78: Item | C78: Falcon Est. Cost | D78: Notes
B79: Retaining Wall, Wood Tie Wells | C79: 15000 | D79: Structural/safety; Falcon estimated $15,000
B80: TOTAL OMITTED | C80: 15000
B82: Prepared October 2026 (re-based to 2027 to match the 2027 budget). Review and update annually.

Sheet Fund Summary
A1: Scarborough Glen Condo Association IV — Fund Summary & Reduction Readiness
A2: Three decoupled funds. Yellow cells are inputs — replace placeholders with actual figures.
A4: SHARED INPUTS
A5: Total Reserve Cash (all accounts): | B5: =SUM(D12:D14) | C5: Auto-total of the three fund starting balances (Allocated Start column).
A6: Number of Units: | B6: 98
A7: Contribution Growth Rate: | B7: 0.03
A8: Interest Rate on Reserves: | B8: 0.01
A10: THE THREE FUNDS
A11: Fund | B11: Target / Floor | C11: Year-1 Contribution | D11: Allocated Start | E11: Floor Rule
A12: 1. Emergency Reserve | B12: 125000 | C12: 23800 | D12: 23100 | E12: Reach & hold target (uninsured structural & shortfall exposure — deductible on HOA)
A13: 2. Long-Term Maintenance | B13: 0 | C13: 135100 | D13: 91605 | E13: Never below $0 (Becht capital schedule)
A14: 3. Operating Reserve | B14: =B38*B37 | C14: 12600 | D14: 61899 | E14: ≥ multiplier x monthly op. expense (set below)
A15: TOTAL | C15: =SUM(C12:C14) | D15: =SUM(D12:D14)
A16: Allocated Start = each fund's current balance (yellow, editable); Total Reserve Cash (B5) is their sum. Recommended: fund near-term Long-Term Maintenance and Operating liquidity first, and build the Emergency Reserve from contributions over time.
A18: LONG-TERM MAINTENANCE — FUNDING HEALTH
A19: Fully Funded Balance (FFB — what LTM should hold today): | B19: 1484351
A20: LTM Reserve (allocated start): | B20: =D13
A21: Percent Funded: | B21: =IF(B19=0,0,B20/B19) | C21: =IF(B21<0.3,"WEAK (<30% - high special-assessment risk)",IF(B21<0.7,"FAIR (30-70%)","STRONG (70%+)"))
A22: CAI bands: under 30% = weak; 30-70% = fair; 70%+ = strong.
A24: RESERVE FUNDING STATUS — ALL THREE MUST BE FUNDED BEFORE ANY REDUCTION
A25: Reserve target | B25: Target | C25: Actual | D25: Status
A26: 1. Emergency Reserve funded to target | B26: =B12 | C26: =D12 | D26: =IF(D12>=B12,"Funded","To be funded")
A27: 2. Long-Term Maintenance never below $0 | B27: 0 | C27: =MIN('Long-Term Maintenance'!F5:F28) | D27: =IF(C27>=B27,"Funded","To be funded")
A28: 3. Operating Reserve at/above its floor | B28: =B14 | C28: =MIN('Operating Reserve'!F5:F28) | D28: =IF(C28>=B28,"Funded","To be funded")
A29: Reduction in common charges | D29: =IF(AND(D26="Funded",D27="Funded",D28="Funded"),"Reduction can be considered","Not yet supported — hold common charges")
A31: Combined Monthly Cost per Unit (Year 1, all three funds): | B31: =(C12+C13+C14)/B6/12
A32: Grows at the Growth Rate each year; this is Year-1. Add the HOA per-unit amount for a unit owner's all-in monthly.
A34: To model a dues reduction: lower a fund's Year-1 Contribution above and watch the status. Any target turning 'To be funded' means the reduction is not supported.
A36: OPERATING RESERVE BASIS
A37: Monthly Operating Expense: | B37: 39286.67 | C37: The association's total monthly operating spend (excludes reserve contributions).
A38: Operating Reserve Multiplier (months, 1-3): | B38: 3 | C38: Operating Reserve floor (row 14) = this multiplier x monthly operating expense.
A40: MONTHLY FUNDING PER UNIT (Year 1)
A41: Fund | B41: $ / unit / month
A42: Emergency Reserve | B42: =C12/$B$6/12
A43: Long-Term Maintenance | B43: =C13/$B$6/12
A44: Operating Reserve | B44: =C14/$B$6/12
A45: TOTAL reserve funding / unit / month | B45: =(C12+C13+C14)/$B$6/12
A46: Equal per-unit split (fund contribution / units / 12); grows ~3%/yr. Excludes the separate $365/unit HOA dues. If common charges are set by percentage interest, larger units pay proportionally more than this average.

Sheet Emergency Reserve
A1: Scarborough Glen Condo Association IV — Emergency Reserve | J1: Floor (from Fund Summary):
A2: All inputs are set on the Fund Summary sheet. This tab is calculated. | J2: ='Fund Summary'!$B$12
A4: Year | B4: Opening Balance | C4: Annual Contribution | D4: Disbursement | E4: Interest Earned | F4: Closing Balance | G4: Monthly Cost/Unit | H4: Status
A5: 2027 | B5: ='Fund Summary'!$D$12 | C5: =IF('Fund Summary'!$D$12>='Fund Summary'!$B$12,0,'Fund Summary'!$C$12) | D5: 0 | E5: =B5*'Fund Summary'!$B$8 | F5: =B5+C5-D5+E5 | G5: =C5/'Fund Summary'!$B$6/12 | H5: =IF(F5>='Fund Summary'!$B$12,"FUNDED","BUILDING")
A6: 2028 | B6: =F5 | C6: =IF(F5>='Fund Summary'!$B$12,0,'Fund Summary'!$C$12*(1+'Fund Summary'!$B$7)^1) | D6: 0 | E6: =B6*'Fund Summary'!$B$8 | F6: =B6+C6-D6+E6 | G6: =C6/'Fund Summary'!$B$6/12 | H6: =IF(F6>='Fund Summary'!$B$12,"FUNDED","BUILDING")
A7: 2029 | B7: =F6 | C7: =IF(F6>='Fund Summary'!$B$12,0,'Fund Summary'!$C$12*(1+'Fund Summary'!$B$7)^2) | D7: 0 | E7: =B7*'Fund Summary'!$B$8 | F7: =B7+C7-D7+E7 | G7: =C7/'Fund Summary'!$B$6/12 | H7: =IF(F7>='Fund Summary'!$B$12,"FUNDED","BUILDING")
A8: 2030 | B8: =F7 | C8: =IF(F7>='Fund Summary'!$B$12,0,'Fund Summary'!$C$12*(1+'Fund Summary'!$B$7)^3) | D8: 0 | E8: =B8*'Fund Summary'!$B$8 | F8: =B8+C8-D8+E8 | G8: =C8/'Fund Summary'!$B$6/12 | H8: =IF(F8>='Fund Summary'!$B$12,"FUNDED","BUILDING")
A9: 2031 | B9: =F8 | C9: =IF(F8>='Fund Summary'!$B$12,0,'Fund Summary'!$C$12*(1+'Fund Summary'!$B$7)^4) | D9: 0 | E9: =B9*'Fund Summary'!$B$8 | F9: =B9+C9-D9+E9 | G9: =C9/'Fund Summary'!$B$6/12 | H9: =IF(F9>='Fund Summary'!$B$12,"FUNDED","BUILDING")
A10: 2032 | B10: =F9 | C10: =IF(F9>='Fund Summary'!$B$12,0,'Fund Summary'!$C$12*(1+'Fund Summary'!$B$7)^5) | D10: 0 | E10: =B10*'Fund Summary'!$B$8 | F10: =B10+C10-D10+E10 | G10: =C10/'Fund Summary'!$B$6/12 | H10: =IF(F10>='Fund Summary'!$B$12,"FUNDED","BUILDING")
A11: 2033 | B11: =F10 | C11: =IF(F10>='Fund Summary'!$B$12,0,'Fund Summary'!$C$12*(1+'Fund Summary'!$B$7)^6) | D11: 0 | E11: =B11*'Fund Summary'!$B$8 | F11: =B11+C11-D11+E11 | G11: =C11/'Fund Summary'!$B$6/12 | H11: =IF(F11>='Fund Summary'!$B$12,"FUNDED","BUILDING")
A12: 2034 | B12: =F11 | C12: =IF(F11>='Fund Summary'!$B$12,0,'Fund Summary'!$C$12*(1+'Fund Summary'!$B$7)^7) | D12: 0 | E12: =B12*'Fund Summary'!$B$8 | F12: =B12+C12-D12+E12 | G12: =C12/'Fund Summary'!$B$6/12 | H12: =IF(F12>='Fund Summary'!$B$12,"FUNDED","BUILDING")
A13: 2035 | B13: =F12 | C13: =IF(F12>='Fund Summary'!$B$12,0,'Fund Summary'!$C$12*(1+'Fund Summary'!$B$7)^8) | D13: 0 | E13: =B13*'Fund Summary'!$B$8 | F13: =B13+C13-D13+E13 | G13: =C13/'Fund Summary'!$B$6/12 | H13: =IF(F13>='Fund Summary'!$B$12,"FUNDED","BUILDING")
A14: 2036 | B14: =F13 | C14: =IF(F13>='Fund Summary'!$B$12,0,'Fund Summary'!$C$12*(1+'Fund Summary'!$B$7)^9) | D14: 0 | E14: =B14*'Fund Summary'!$B$8 | F14: =B14+C14-D14+E14 | G14: =C14/'Fund Summary'!$B$6/12 | H14: =IF(F14>='Fund Summary'!$B$12,"FUNDED","BUILDING")
A15: 2037 | B15: =F14 | C15: =IF(F14>='Fund Summary'!$B$12,0,'Fund Summary'!$C$12*(1+'Fund Summary'!$B$7)^10) | D15: 0 | E15: =B15*'Fund Summary'!$B$8 | F15: =B15+C15-D15+E15 | G15: =C15/'Fund Summary'!$B$6/12 | H15: =IF(F15>='Fund Summary'!$B$12,"FUNDED","BUILDING")
A16: 2038 | B16: =F15 | C16: =IF(F15>='Fund Summary'!$B$12,0,'Fund Summary'!$C$12*(1+'Fund Summary'!$B$7)^11) | D16: 0 | E16: =B16*'Fund Summary'!$B$8 | F16: =B16+C16-D16+E16 | G16: =C16/'Fund Summary'!$B$6/12 | H16: =IF(F16>='Fund Summary'!$B$12,"FUNDED","BUILDING")
A17: 2039 | B17: =F16 | C17: =IF(F16>='Fund Summary'!$B$12,0,'Fund Summary'!$C$12*(1+'Fund Summary'!$B$7)^12) | D17: 0 | E17: =B17*'Fund Summary'!$B$8 | F17: =B17+C17-D17+E17 | G17: =C17/'Fund Summary'!$B$6/12 | H17: =IF(F17>='Fund Summary'!$B$12,"FUNDED","BUILDING")
A18: 2040 | B18: =F17 | C18: =IF(F17>='Fund Summary'!$B$12,0,'Fund Summary'!$C$12*(1+'Fund Summary'!$B$7)^13) | D18: 0 | E18: =B18*'Fund Summary'!$B$8 | F18: =B18+C18-D18+E18 | G18: =C18/'Fund Summary'!$B$6/12 | H18: =IF(F18>='Fund Summary'!$B$12,"FUNDED","BUILDING")
A19: 2041 | B19: =F18 | C19: =IF(F18>='Fund Summary'!$B$12,0,'Fund Summary'!$C$12*(1+'Fund Summary'!$B$7)^14) | D19: 0 | E19: =B19*'Fund Summary'!$B$8 | F19: =B19+C19-D19+E19 | G19: =C19/'Fund Summary'!$B$6/12 | H19: =IF(F19>='Fund Summary'!$B$12,"FUNDED","BUILDING")
A20: 2042 | B20: =F19 | C20: =IF(F19>='Fund Summary'!$B$12,0,'Fund Summary'!$C$12*(1+'Fund Summary'!$B$7)^15) | D20: 0 | E20: =B20*'Fund Summary'!$B$8 | F20: =B20+C20-D20+E20 | G20: =C20/'Fund Summary'!$B$6/12 | H20: =IF(F20>='Fund Summary'!$B$12,"FUNDED","BUILDING")
A21: 2043 | B21: =F20 | C21: =IF(F20>='Fund Summary'!$B$12,0,'Fund Summary'!$C$12*(1+'Fund Summary'!$B$7)^16) | D21: 0 | E21: =B21*'Fund Summary'!$B$8 | F21: =B21+C21-D21+E21 | G21: =C21/'Fund Summary'!$B$6/12 | H21: =IF(F21>='Fund Summary'!$B$12,"FUNDED","BUILDING")
A22: 2044 | B22: =F21 | C22: =IF(F21>='Fund Summary'!$B$12,0,'Fund Summary'!$C$12*(1+'Fund Summary'!$B$7)^17) | D22: 0 | E22: =B22*'Fund Summary'!$B$8 | F22: =B22+C22-D22+E22 | G22: =C22/'Fund Summary'!$B$6/12 | H22: =IF(F22>='Fund Summary'!$B$12,"FUNDED","BUILDING")
A23: 2045 | B23: =F22 | C23: =IF(F22>='Fund Summary'!$B$12,0,'Fund Summary'!$C$12*(1+'Fund Summary'!$B$7)^18) | D23: 0 | E23: =B23*'Fund Summary'!$B$8 | F23: =B23+C23-D23+E23 | G23: =C23/'Fund Summary'!$B$6/12 | H23: =IF(F23>='Fund Summary'!$B$12,"FUNDED","BUILDING")
A24: 2046 | B24: =F23 | C24: =IF(F23>='Fund Summary'!$B$12,0,'Fund Summary'!$C$12*(1+'Fund Summary'!$B$7)^19) | D24: 0 | E24: =B24*'Fund Summary'!$B$8 | F24: =B24+C24-D24+E24 | G24: =C24/'Fund Summary'!$B$6/12 | H24: =IF(F24>='Fund Summary'!$B$12,"FUNDED","BUILDING")
A25: 2047 | B25: =F24 | C25: =IF(F24>='Fund Summary'!$B$12,0,'Fund Summary'!$C$12*(1+'Fund Summary'!$B$7)^20) | D25: 0 | E25: =B25*'Fund Summary'!$B$8 | F25: =B25+C25-D25+E25 | G25: =C25/'Fund Summary'!$B$6/12 | H25: =IF(F25>='Fund Summary'!$B$12,"FUNDED","BUILDING")
A26: 2048 | B26: =F25 | C26: =IF(F25>='Fund Summary'!$B$12,0,'Fund Summary'!$C$12*(1+'Fund Summary'!$B$7)^21) | D26: 0 | E26: =B26*'Fund Summary'!$B$8 | F26: =B26+C26-D26+E26 | G26: =C26/'Fund Summary'!$B$6/12 | H26: =IF(F26>='Fund Summary'!$B$12,"FUNDED","BUILDING")
A27: 2049 | B27: =F26 | C27: =IF(F26>='Fund Summary'!$B$12,0,'Fund Summary'!$C$12*(1+'Fund Summary'!$B$7)^22) | D27: 0 | E27: =B27*'Fund Summary'!$B$8 | F27: =B27+C27-D27+E27 | G27: =C27/'Fund Summary'!$B$6/12 | H27: =IF(F27>='Fund Summary'!$B$12,"FUNDED","BUILDING")
A28: 2050 | B28: =F27 | C28: =IF(F27>='Fund Summary'!$B$12,0,'Fund Summary'!$C$12*(1+'Fund Summary'!$B$7)^23) | D28: 0 | E28: =B28*'Fund Summary'!$B$8 | F28: =B28+C28-D28+E28 | G28: =C28/'Fund Summary'!$B$6/12 | H28: =IF(F28>='Fund Summary'!$B$12,"FUNDED","BUILDING")
A29: TOTAL | C29: =SUM(C5:C28) | D29: =SUM(D5:D28) | E29: =SUM(E5:E28)

Sheet Long-Term Maintenance
A1: Scarborough Glen Condo Association IV — Long-Term Maintenance
A2: All inputs are set on the Fund Summary sheet. This tab is calculated.
A4: Year | B4: Opening Balance | C4: Annual Contribution | D4: Disbursement | E4: Interest Earned | F4: Closing Balance | G4: Monthly Cost/Unit | H4: Status
A5: 2027 | B5: ='Fund Summary'!$D$13 | C5: ='Fund Summary'!$C$13 | D5: 88065 | E5: =B5*'Fund Summary'!$B$8 | F5: =B5+C5-D5+E5 | G5: =C5/'Fund Summary'!$B$6/12 | H5: =IF(F5<0,"BELOW $0","")
A6: 2028 | B6: =F5 | C6: =C5*(1+'Fund Summary'!$B$7) | D6: 158498 | E6: =B6*'Fund Summary'!$B$8 | F6: =B6+C6-D6+E6 | G6: =C6/'Fund Summary'!$B$6/12 | H6: =IF(F6<0,"BELOW $0","")
A7: 2029 | B7: =F6 | C7: =C6*(1+'Fund Summary'!$B$7) | D7: 0 | E7: =B7*'Fund Summary'!$B$8 | F7: =B7+C7-D7+E7 | G7: =C7/'Fund Summary'!$B$6/12 | H7: =IF(F7<0,"BELOW $0","")
A8: 2030 | B8: =F7 | C8: =C7*(1+'Fund Summary'!$B$7) | D8: 0 | E8: =B8*'Fund Summary'!$B$8 | F8: =B8+C8-D8+E8 | G8: =C8/'Fund Summary'!$B$6/12 | H8: =IF(F8<0,"BELOW $0","")
A9: 2031 | B9: =F8 | C9: =C8*(1+'Fund Summary'!$B$7) | D9: 145095 | E9: =B9*'Fund Summary'!$B$8 | F9: =B9+C9-D9+E9 | G9: =C9/'Fund Summary'!$B$6/12 | H9: =IF(F9<0,"BELOW $0","")
A10: 2032 | B10: =F9 | C10: =C9*(1+'Fund Summary'!$B$7) | D10: 234034 | E10: =B10*'Fund Summary'!$B$8 | F10: =B10+C10-D10+E10 | G10: =C10/'Fund Summary'!$B$6/12 | H10: =IF(F10<0,"BELOW $0","")
A11: 2033 | B11: =F10 | C11: =C10*(1+'Fund Summary'!$B$7) | D11: 478913 | E11: =B11*'Fund Summary'!$B$8 | F11: =B11+C11-D11+E11 | G11: =C11/'Fund Summary'!$B$6/12 | H11: =IF(F11<0,"BELOW $0","")
A12: 2034 | B12: =F11 | C12: =C11*(1+'Fund Summary'!$B$7) | D12: 0 | E12: =B12*'Fund Summary'!$B$8 | F12: =B12+C12-D12+E12 | G12: =C12/'Fund Summary'!$B$6/12 | H12: =IF(F12<0,"BELOW $0","")
A13: 2035 | B13: =F12 | C13: =C12*(1+'Fund Summary'!$B$7) | D13: 38360 | E13: =B13*'Fund Summary'!$B$8 | F13: =B13+C13-D13+E13 | G13: =C13/'Fund Summary'!$B$6/12 | H13: =IF(F13<0,"BELOW $0","")
A14: 2036 | B14: =F13 | C14: =C13*(1+'Fund Summary'!$B$7) | D14: 0 | E14: =B14*'Fund Summary'!$B$8 | F14: =B14+C14-D14+E14 | G14: =C14/'Fund Summary'!$B$6/12 | H14: =IF(F14<0,"BELOW $0","")
A15: 2037 | B15: =F14 | C15: =C14*(1+'Fund Summary'!$B$7) | D15: 0 | E15: =B15*'Fund Summary'!$B$8 | F15: =B15+C15-D15+E15 | G15: =C15/'Fund Summary'!$B$6/12 | H15: =IF(F15<0,"BELOW $0","")
A16: 2038 | B16: =F15 | C16: =C15*(1+'Fund Summary'!$B$7) | D16: 0 | E16: =B16*'Fund Summary'!$B$8 | F16: =B16+C16-D16+E16 | G16: =C16/'Fund Summary'!$B$6/12 | H16: =IF(F16<0,"BELOW $0","")
A17: 2039 | B17: =F16 | C17: =C16*(1+'Fund Summary'!$B$7) | D17: 22028 | E17: =B17*'Fund Summary'!$B$8 | F17: =B17+C17-D17+E17 | G17: =C17/'Fund Summary'!$B$6/12 | H17: =IF(F17<0,"BELOW $0","")
... A28: 2050 | B28: =F27 | C28: =C27*(1+'Fund Summary'!$B$7) | D28: 0 | E28: =B28*'Fund Summary'!$B$8 | F28: =B28+C28-D28+E28 | G28: =C28/'Fund Summary'!$B$6/12 | H28: =IF(F28<0,"BELOW $0","")
A29: TOTAL | C29: =SUM(C5:C28) | D29: =SUM(D5:D28) | E29: =SUM(E5:E28)

Sheet Operating Reserve
A1: Scarborough Glen Condo Association IV — Operating Reserve | J1: Floor (from Fund Summary):
A2: All inputs are set on the Fund Summary sheet. This tab is calculated. | J2: ='Fund Summary'!$B$14
A4: Year | B4: Opening Balance | C4: Annual Contribution | D4: Disbursement | E4: Interest Earned | F4: Closing Balance | G4: Monthly Cost/Unit | H4: Status
A5: 2027 | B5: ='Fund Summary'!$D$14 | C5: =IF('Fund Summary'!$D$14>='Fund Summary'!$B$14,0,'Fund Summary'!$C$14) | D5: 0 | E5: =B5*'Fund Summary'!$B$8 | F5: =B5+C5-D5+E5 | G5: =C5/'Fund Summary'!$B$6/12 | H5: =IF(F5<'Fund Summary'!$B$14,"BELOW FLOOR","")
A6: 2028 | B6: =F5 | C6: =IF(F5>='Fund Summary'!$B$14,0,'Fund Summary'!$C$14*(1+'Fund Summary'!$B$7)^1) | D6: 0 | E6: =B6*'Fund Summary'!$B$8 | F6: =B6+C6-D6+E6 | G6: =C6/'Fund Summary'!$B$6/12 | H6: =IF(F6<'Fund Summary'!$B$14,"BELOW FLOOR","")
A7: 2029 | B7: =F6 | C7: =IF(F6>='Fund Summary'!$B$14,0,'Fund Summary'!$C$14*(1+'Fund Summary'!$B$7)^2) | D7: 0 | E7: =B7*'Fund Summary'!$B$8 | F7: =B7+C7-D7+E7 | G7: =C7/'Fund Summary'!$B$6/12 | H7: =IF(F7<'Fund Summary'!$B$14,"BELOW FLOOR","")
A8: 2030 | B8: =F7 | C8: =IF(F7>='Fund Summary'!$B$14,0,'Fund Summary'!$C$14*(1+'Fund Summary'!$B$7)^3) | D8: 0 | E8: =B8*'Fund Summary'!$B$8 | F8: =B8+C8-D8+E8 | G8: =C8/'Fund Summary'!$B$6/12 | H8: =IF(F8<'Fund Summary'!$B$14,"BELOW FLOOR","")
A9: 2031 | B9: =F8 | C9: =IF(F8>='Fund Summary'!$B$14,0,'Fund Summary'!$C$14*(1+'Fund Summary'!$B$7)^4) | D9: 0 | E9: =B9*'Fund Summary'!$B$8 | F9: =B9+C9-D9+E9 | G9: =C9/'Fund Summary'!$B$6/12 | H9: =IF(F9<'Fund Summary'!$B$14,"BELOW FLOOR","")
A10: 2032 | B10: =F9 | C10: =IF(F9>='Fund Summary'!$B$14,0,'Fund Summary'!$C$14*(1+'Fund Summary'!$B$7)^5) | D10: 0 | E10: =B10*'Fund Summary'!$B$8 | F10: =B10+C10-D10+E10 | G10: =C10/'Fund Summary'!$B$6/12 | H10: =IF(F10<'Fund Summary'!$B$14,"BELOW FLOOR","")
A11: 2033 | B11: =F10 | C11: =IF(F10>='Fund Summary'!$B$14,0,'Fund Summary'!$C$14*(1+'Fund Summary'!$B$7)^6) | D11: 0 | E11: =B11*'Fund Summary'!$B$8 | F11: =B11+C11-D11+E11 | G11: =C11/'Fund Summary'!$B$6/12 | H11: =IF(F11<'Fund Summary'!$B$14,"BELOW FLOOR","")
A12: 2034 | B12: =F11 | C12: =IF(F11>='Fund Summary'!$B$14,0,'Fund Summary'!$C$14*(1+'Fund Summary'!$B$7)^7) | D12: 0 | E12: =B12*'Fund Summary'!$B$8 | F12: =B12+C12-D12+E12 | G12: =C12/'Fund Summary'!$B$6/12 | H12: =IF(F12<'Fund Summary'!$B$14,"BELOW FLOOR","")
A13: 2035 | B13: =F12 | C13: =IF(F12>='Fund Summary'!$B$14,0,'Fund Summary'!$C$14*(1+'Fund Summary'!$B$7)^8) | D13: 0 | E13: =B13*'Fund Summary'!$B$8 | F13: =B13+C13-D13+E13 | G13: =C13/'Fund Summary'!$B$6/12 | H13: =IF(F13<'Fund Summary'!$B$14,"BELOW FLOOR","")
A14: 2036 | B14: =F13 | C14: =IF(F13>='Fund Summary'!$B$14,0,'Fund Summary'!$C$14*(1+'Fund Summary'!$B$7)^9) | D14: 0 | E14: =B14*'Fund Summary'!$B$8 | F14: =B14+C14-D14+E14 | G14: =C14/'Fund Summary'!$B$6/12 | H14: =IF(F14<'Fund Summary'!$B$14,"BELOW FLOOR","")
A15: 2037 | B15: =F14 | C15: =IF(F14>='Fund Summary'!$B$14,0,'Fund Summary'!$C$14*(1+'Fund Summary'!$B$7)^10) | D15: 0 | E15: =B15*'Fund Summary'!$B$8 | F15: =B15+C15-D15+E15 | G15: =C15/'Fund Summary'!$B$6/12 | H15: =IF(F15<'Fund Summary'!$B$14,"BELOW FLOOR","")
A16: 2038 | B16: =F15 | C16: =IF(F15>='Fund Summary'!$B$14,0,'Fund Summary'!$C$14*(1+'Fund Summary'!$B$7)^11) | D16: 0 | E16: =B16*'Fund Summary'!$B$8 | F16: =B16+C16-D16+E16 | G16: =C16/'Fund Summary'!$B$6/12 | H16: =IF(F16<'Fund Summary'!$B$14,"BELOW FLOOR","")
A17: 2039 | B17: =F16 | C17: =IF(F16>='Fund Summary'!$B$14,0,'Fund Summary'!$C$14*(1+'Fund Summary'!$B$7)^12) | D17: 0 | E17: =B17*'Fund Summary'!$B$8 | F17: =B17+C17-D17+E17 | G17: =C17/'Fund Summary'!$B$6/12 | H17: =IF(F17<'Fund Summary'!$B$14,"BELOW FLOOR","")
A18: 2040 | B18: =F17 | C18: =IF(F17>='Fund Summary'!$B$14,0,'Fund Summary'!$C$14*(1+'Fund Summary'!$B$7)^13) | D18: 0 | E18: =B18*'Fund Summary'!$B$8 | F18: =B18+C18-D18+E18 | G18: =C18/'Fund Summary'!$B$6/12 | H18: =IF(F18<'Fund Summary'!$B$14,"BELOW FLOOR","")
A19: 2041 | B19: =F18 | C19: =IF(F18>='Fund Summary'!$B$14,0,'Fund Summary'!$C$14*(1+'Fund Summary'!$B$7)^14) | D19: 0 | E19: =B19*'Fund Summary'!$B$8 | F19: =B19+C19-D19+E19 | G19: =C19/'Fund Summary'!$B$6/12 | H19: =IF(F19<'Fund Summary'!$B$14,"BELOW FLOOR","")
A20: 2042 | B20: =F19 | C20: =IF(F19>='Fund Summary'!$B$14,0,'Fund Summary'!$C$14*(1+'Fund Summary'!$B$7)^15) | D20: 0 | E20: =B20*'Fund Summary'!$B$8 | F20: =B20+C20-D20+E20 | G20: =C20/'Fund Summary'!$B$6/12 | H20: =IF(F20<'Fund Summary'!$B$14,"BELOW FLOOR","")
A21: 2043 | B21: =F20 | C21: =IF(F20>='Fund Summary'!$B$14,0,'Fund Summary'!$C$14*(1+'Fund Summary'!$B$7)^16) | D21: 0 | E21: =B21*'Fund Summary'!$B$8 | F21: =B21+C21-D21+E21 | G21: =C21/'Fund Summary'!$B$6/12 | H21: =IF(F21<'Fund Summary'!$B$14,"BELOW FLOOR","")
A22: 2044 | B22: =F21 | C22: =IF(F21>='Fund Summary'!$B$14,0,'Fund Summary'!$C$14*(1+'Fund Summary'!$B$7)^17) | D22: 0 | E22: =B22*'Fund Summary'!$B$8 | F22: =B22+C22-D22+E22 | G22: =C22/'Fund Summary'!$B$6/12 | H22: =IF(F22<'Fund Summary'!$B$14,"BELOW FLOOR","")
A23: 2045 | B23: =F22 | C23: =IF(F22>='Fund Summary'!$B$14,0,'Fund Summary'!$C$14*(1+'Fund Summary'!$B$7)^18) | D23: 0 | E23: =B23*'Fund Summary'!$B$8 | F23: =B23+C23-D23+E23 | G23: =C23/'Fund Summary'!$B$6/12 | H23: =IF(F23<'Fund Summary'!$B$14,"BELOW FLOOR","")
A24: 2046 | B24: =F23 | C24: =IF(F23>='Fund Summary'!$B$14,0,'Fund Summary'!$C$14*(1+'Fund Summary'!$B$7)^19) | D24: 0 | E24: =B24*'Fund Summary'!$B$8 | F24: =B24+C24-D24+E24 | G24: =C24/'Fund Summary'!$B$6/12 | H24: =IF(F24<'Fund Summary'!$B$14,"BELOW FLOOR","")
A25: 2047 | B25: =F24 | C25: =IF(F24>='Fund Summary'!$B$14,0,'Fund Summary'!$C$14*(1+'Fund Summary'!$B$7)^20) | D25: 0 | E25: =B25*'Fund Summary'!$B$8 | F25: =B25+C25-D25+E25 | G25: =C25/'Fund Summary'!$B$6/12 | H25: =IF(F25<'Fund Summary'!$B$14,"BELOW FLOOR","")
A26: 2048 | B26: =F25 | C26: =IF(F25>='Fund Summary'!$B$14,0,'Fund Summary'!$C$14*(1+'Fund Summary'!$B$7)^21) | D26: 0 | E26: =B26*'Fund Summary'!$B$8 | F26: =B26+C26-D26+E26 | G26: =C26/'Fund Summary'!$B$6/12 | H26: =IF(F26<'Fund Summary'!$B$14,"BELOW FLOOR","")
A27: 2049 | B27: =F26 | C27: =IF(F26>='Fund Summary'!$B$14,0,'Fund Summary'!$C$14*(1+'Fund Summary'!$B$7)^22) | D27: 0 | E27: =B27*'Fund Summary'!$B$8 | F27: =B27+C27-D27+E27 | G27: =C27/'Fund Summary'!$B$6/12 | H27: =IF(F27<'Fund Summary'!$B$14,"BELOW FLOOR","")
A28: 2050 | B28: =F27 | C28: =IF(F27>='Fund Summary'!$B$14,0,'Fund Summary'!$C$14*(1+'Fund Summary'!$B$7)^23) | D28: 0 | E28: =B28*'Fund Summary'!$B$8 | F28: =B28+C28-D28+E28 | G28: =C28/'Fund Summary'!$B$6/12 | H28: =IF(F28<'Fund Summary'!$B$14,"BELOW FLOOR","")
A29: TOTAL | C29: =SUM(C5:C28) | D29: =SUM(D5:D28) | E29: =SUM(E5:E28)

Sheet Components
A1: Scarborough Glen Condo Association IV — Component Detail
A2: All costs from Becht Engineering Capital Reserve Study (2026)
A4: Component | B4: Becht Community Total | C4: Entity Share % | D4: Entity Allocated Cost | E4: Replacement Year | F4: Inflated Cost at Replacement
A5: Siding, Vinyl (Condo IV share) | B5: 1800000 | C5: 0.9177 | D5: 1651860 | E5: 2049 | F5: 3260083
A6: Roof, Shingles - Townhouses (Condo IV share) | B6: 1150988 | C6: 0.7646 | D6: 880045 | E6: 2050 | F6: Beyond plan horizon
A7: Deck Framing & Footings, Wood (Condo IV share) | B7: 440000 | C7: 0.3679 | D7: 149760 | E7: 2033 | F7: 184186
A8: Deck Boards (surface), Wood (Condo IV share) | B8: 440000 | C8: 0.3679 | D8: 131040 | E8: 2033 | F8: 161163
A9: Deck Railings & Balusters, Wood (Condo IV share) (safety) | B9: 440000 | C9: 0.3679 | D9: 93600 | E9: 2033 | F9: 115116
A10: Deck Railings — 2027 remaining replacements (5 rails) | C10: 1 | D10: 22500 | E10: 2027 | F10: 23175
A11: Deck Replacement, Composite (Condo IV share) | B11: 360000 | C11: 0.3679 | D11: 132444 | E11: 2053 (beyond plan) | F11: Beyond plan horizon
A12: Chimney Chase Covers (Condo IV share) | B12: 178800 | C12: 0.7 | D12: 125160 | E12: 2031 | F12: 145095
A13: Entry Stoops — Concrete Replacement | C13: 1 | D13: 196000 | E13: 2032 | F13: 234034
A14: Entry Stoops — Leveling & Stair Nosing (safety) | C14: 1 | D14: 29400 | E14: 2028 | F14: 31190
A15: Exterior Caulk/Sealant & Trim Maintenance | C15: 1 | D15: 15000 | E15: 2027 | F15: 15450
A16: Window Wells — rebuild program, 2027 (6 wells) | C16: 1 | D16: 48000 | E16: 2027 | F16: 49440
A17: Window Wells — rebuild program, 2028 (15 wells) | C17: 1 | D17: 120000 | E17: 2028 | F17: 127308
A18: TOTAL | D18: 3594809

Sheet Expenditure Chart
A1: COLOR KEY | E1: CHART DATA
A2: Color | B2: Component | C2: 25-Year Total | E2: Year | F2: Chimney Chase Covers | G2: Deck Boards (surface) | H2: Deck Framing & Footings | I2: Deck Railings & Balusters (safety) | J2: Entry Stoops — Concrete Replacement | K2: Entry Stoops — Leveling & Stair Nosing (safety) | L2: Exterior Caulk/Sealant & Trim Maintenance | M2: Siding, Vinyl | N2: Window Wells (rebuild program)
B3: Chimney Chase Covers | C3: 145095 | E3: 2027 | I3: 23175 | L3: 15450 | N3: 49440
B4: Deck Boards (surface) | C4: 161163 | E4: 2028 | K4: 31190 | N4: 127308
B5: Deck Framing & Footings | C5: 184186 | E5: 2031 | F5: 145095
B6: Deck Railings & Balusters (safety) | C6: 302419 | E6: 2032 | J6: 234034
B7: Entry Stoops — Concrete Replacement | C7: 234034 | E7: 2033 | G7: 161163 | H7: 184186 | I7: 115116 | L7: 18448
B8: Entry Stoops — Leveling & Stair Nosing (safety) | C8: 174751 | E8: 2035 | K8: 38360
B9: Exterior Caulk/Sealant & Trim Maintenance | C9: 82229 | E9: 2039 | L9: 22028
B10: Siding, Vinyl | C10: 3260083 | E10: 2042 | K10: 47178
B11: Window Wells (rebuild program) | C11: 176748 | E11: 2045 | I11: 164128 | L11: 26303
E12: 2049 | K12: 58023 | M12: 3260083
